{
  "headers": [
    "INDUSTRY PERSPECTIVES — M13: MEDIA BUYING"
  ],
  "rows": [
    {
      "INDUSTRY PERSPECTIVES — M13: MEDIA BUYING": "RESEARCH QUESTIONS"
    },
    {
      "INDUSTRY PERSPECTIVES — M13: MEDIA BUYING": "Current CPMs on Meta/TikTok/YouTube for supplement targeting? Account structures? Attribution post-iOS? Media buying team structures?"
    },
    {
      "INDUSTRY PERSPECTIVES — M13: MEDIA BUYING": "CURRENT STATE"
    },
    {
      "INDUSTRY PERSPECTIVES — M13: MEDIA BUYING": "[What does this domain look like right now? Key players, standard practices, consensus view.]"
    },
    {
      "INDUSTRY PERSPECTIVES — M13: MEDIA BUYING": "BEST IN CLASS"
    },
    {
      "INDUSTRY PERSPECTIVES — M13: MEDIA BUYING": "[Who does this exceptionally well? What specifically makes them good? What can we steal?]"
    },
    {
      "INDUSTRY PERSPECTIVES — M13: MEDIA BUYING": "WHERE THE INDUSTRY IS WRONG"
    },
    {
      "INDUSTRY PERSPECTIVES — M13: MEDIA BUYING": "[Conventional wisdom that's wrong or outdated. Assumptions that don't hold.]"
    },
    {
      "INDUSTRY PERSPECTIVES — M13: MEDIA BUYING": "OUR CONTRARIAN TAKE"
    },
    {
      "INDUSTRY PERSPECTIVES — M13: MEDIA BUYING": "[What we believe that most would disagree with. Why we're right.]"
    },
    {
      "INDUSTRY PERSPECTIVES — M13: MEDIA BUYING": "IMPLICATIONS FOR IONWAVE"
    },
    {
      "INDUSTRY PERSPECTIVES — M13: MEDIA BUYING": "[What we do differently. What we steal. What we avoid.]"
    }
  ],
  "row_count": 12,
  "sheet_name": "IP-M13",
  "sheet_index": 356
}