{
  "headers": [
    "INDUSTRY PERSPECTIVES — S3: INFRASTRUCTURE & FUNDRAISING"
  ],
  "rows": [
    {
      "INDUSTRY PERSPECTIVES — S3: INFRASTRUCTURE & FUNDRAISING": "RESEARCH QUESTIONS"
    },
    {
      "INDUSTRY PERSPECTIVES — S3: INFRASTRUCTURE & FUNDRAISING": "How do hedge funds structure thesis-to-execution? How did Rocket Internet, Idealab build venture factories? How do working DAOs (MakerDAO, Gitcoin) govern? What does Remedy-style DR teach about dual-audience sites?"
    },
    {
      "INDUSTRY PERSPECTIVES — S3: INFRASTRUCTURE & FUNDRAISING": "CURRENT STATE"
    },
    {
      "INDUSTRY PERSPECTIVES — S3: INFRASTRUCTURE & FUNDRAISING": "[What does this domain look like right now? Key players, standard practices, consensus view.]"
    },
    {
      "INDUSTRY PERSPECTIVES — S3: INFRASTRUCTURE & FUNDRAISING": "BEST IN CLASS"
    },
    {
      "INDUSTRY PERSPECTIVES — S3: INFRASTRUCTURE & FUNDRAISING": "[Who does this exceptionally well? What specifically makes them good? What can we steal?]"
    },
    {
      "INDUSTRY PERSPECTIVES — S3: INFRASTRUCTURE & FUNDRAISING": "WHERE THE INDUSTRY IS WRONG"
    },
    {
      "INDUSTRY PERSPECTIVES — S3: INFRASTRUCTURE & FUNDRAISING": "[Conventional wisdom that's wrong or outdated. Assumptions that don't hold.]"
    },
    {
      "INDUSTRY PERSPECTIVES — S3: INFRASTRUCTURE & FUNDRAISING": "OUR CONTRARIAN TAKE"
    },
    {
      "INDUSTRY PERSPECTIVES — S3: INFRASTRUCTURE & FUNDRAISING": "[What we believe that most would disagree with. Why we're right.]"
    },
    {
      "INDUSTRY PERSPECTIVES — S3: INFRASTRUCTURE & FUNDRAISING": "IMPLICATIONS FOR IONWAVE"
    },
    {
      "INDUSTRY PERSPECTIVES — S3: INFRASTRUCTURE & FUNDRAISING": "[What we do differently. What we steal. What we avoid.]"
    }
  ],
  "row_count": 12,
  "sheet_name": "IP-S3",
  "sheet_index": 56
}